mixtape/__init__.py
mixtape/base.py
mixtape/events.py
mixtape/exceptions.py
mixtape/players.py
mixtape/py.typed
mixtape/features/__init__.py
mixtape/features/cmdline.py
mixtape/features/console.py
mixtape/features/dbus.py
mixtape/features/http.py
mixtape-0.5.1.dist-info/LICENSE
mixtape-0.5.1.dist-info/METADATA
mixtape-0.5.1.dist-info/WHEEL
mixtape-0.5.1.dist-info/top_level.txt
mixtape-0.5.1.dist-info/RECORD
