Metadata-Version: 2.1
Name: mixtape
Version: 0.5.1
Summary: Gstreamer python application mini-framework
Home-page: https://github.com/ashwoods/mixtape
Author: Ashley Camba Garrido
Author-email: ashwoods@gmail.com
License: MIT
Platform: UNKNOWN
Classifier: Development Status :: 2 - Pre-Alpha
Classifier: Intended Audience :: Developers
Classifier: License :: OSI Approved :: MIT License
Classifier: Operating System :: OS Independent
Classifier: Programming Language :: Python
Classifier: Programming Language :: Python :: 3.6
Classifier: Programming Language :: Python :: 3.7
Classifier: Programming Language :: Python :: 3.8
Classifier: Topic :: Software Development :: Libraries :: Python Modules
Requires-Dist: attrs
Requires-Dist: beppu
Provides-Extra: test
Requires-Dist: pytest (==5.4.2) ; extra == 'test'
Requires-Dist: pytest-asyncio (==0.12.0) ; extra == 'test'
Requires-Dist: pytest-benchmark (==3.2.3) ; extra == 'test'
Requires-Dist: pytest-black (==0.3.9) ; extra == 'test'
Requires-Dist: pytest-cov (==2.9.0) ; extra == 'test'
Requires-Dist: pytest-flake8 (==1.0.6) ; extra == 'test'
Requires-Dist: pytest-forked (==1.1.3) ; extra == 'test'
Requires-Dist: pytest-leaks (==0.3.1) ; extra == 'test'
Requires-Dist: pytest-mock (==3.1.0) ; extra == 'test'
Requires-Dist: pytest-mypy (==0.6.2) ; extra == 'test'
Requires-Dist: pytest-mypy-plugins (==1.3.0) ; extra == 'test'
Requires-Dist: pytest-profiling (==1.7.0) ; extra == 'test'
Requires-Dist: pytest-pylint (==0.17.0) ; extra == 'test'
Requires-Dist: pytest-stub (==1.1.0) ; extra == 'test'
Requires-Dist: pytest-timeout (==1.3.4) ; extra == 'test'
Requires-Dist: pytest-xdist (==1.32.0) ; extra == 'test'
Requires-Dist: colorlog (==4.1.0) ; extra == 'test'
Requires-Dist: flake8 (==3.8.2) ; extra == 'test'
Requires-Dist: flake8-bandit (==2.1.2) ; extra == 'test'
Requires-Dist: flake8-bugbear (==20.1.4) ; extra == 'test'
Requires-Dist: flake8-aaa (==0.10.0) ; extra == 'test'
Requires-Dist: pdbpp (==0.10.2) ; extra == 'test'
